<?xml version="1.0" encoding="utf-8"?>
<Category xmlns:xsd="http://www.w3.org/2001/XMLSchema" xmlns:xsi="http://www.w3.org/2001/XMLSchema-instance" name="TalentTree" description="">
  <Node name="currentlevel">
    <Key key="Name" value="Current level:" />
  </Node>
  <Node name="nextlevel">
    <Key key="Name" value="Next level:" />
  </Node>
  <Node name="w1v1">
    <Key key="Name" value="Stacking Strength" />
    <Key key="Description" value="The character deals 1% more damage for each positive effect lasting more than a minute that is active on them, up to a maximum of 5%." />
  </Node>
  <Node name="w1v2">
    <Key key="Name" value="Dynamic Damage Boost" />
    <Key key="Description" value="The character deals 1% more damage for each ability used within the last 10 seconds, up to a maximum of 5%." />
  </Node>
  <Node name="w1v3">
    <Key key="Name" value="Rampage Rush" />
    <Key key="Description" value="After entering combat, the character gains +5% damage for 10 seconds." />
  </Node>
  <Node name="w1v4">
    <Key key="Name" value="Moving target" />
    <Key key="Description" value="Increase {{EffectCreator.Effect.nm}}." />
    <Key key="Level" value="{{EffectCreator.Effect.nm}}: +{{EffectCreator.Effect.val}}" />
  </Node>
  <Node name="w1v5">
    <Key key="Name" value="Keen eye" />
    <Key key="Description" value="Increase {{EffectCreator.Effect.nm}}." />
    <Key key="Level" value="{{EffectCreator.Effect.nm}}: +{{EffectCreator.Effect.val}}" />
  </Node>
  <Node name="w2v1">
    <Key key="Name" value="Multi-Strike Mastery" />
    <Key key="Description" value="When dealing damage with an ability to more than one target, damage is increased by 2% for each additional target hit. Up to 5 targets. Lasts for 10 seconds." />
  </Node>
  <Node name="w2v2">
    <Key key="Name" value="Healthy Aggression" />
    <Key key="Description" value="The character deals 8% more damage when their health is above 90%." />
  </Node>
  <Node name="w2v3">
    <Key key="Name" value="Adrenaline Rush" />
    <Key key="Description" value="After killing an enemy, the character deals 8% more damage for 10 seconds." />
  </Node>
  <Node name="w2v4">
    <Key key="Name" value="Bloodthirst" />
    <Key key="Description" value="Increase {{EffectCreator.Effect.nm}}." />
    <Key key="Level" value="{{EffectCreator.Effect.nm}}: +{{EffectCreator.Effect.val}}" />
  </Node>
  <Node name="w3v1">
    <Key key="Name" value="Executioner's Edge" />
    <Key key="Description" value="The character deals 10% more damage to targets with health below 20%." />
  </Node>
  <Node name="w3v2">
    <Key key="Name" value="Resilient Fury" />
    <Key key="Description" value="If the character takes damage exceeding 30% of their maximum health within 3 seconds, they deal 10% more damage. The effect lasts for 10 seconds." />
  </Node>
  <Node name="w3v3">
    <Key key="Name" value="Anti-Heal" />
    <Key key="Description" value="Damage-dealing abilities reduce the effectiveness of healing by 40% for 3 seconds." />
  </Node>
  <Node name="w4v1">
    <Key key="Name" value="Fighting Spirit" />
    <Key key="Description" value="Every 2.5 seconds the character spends in combat, they gain 1% attack power or spell power (adaptive) (max 10%)." />
  </Node>
  <Node name="w4v2">
    <Key key="Name" value="Life Force Augmentation" />
    <Key key="Description" value="The character gains additional attack power or spell power (adaptive) equal to 1.5% of their maximum health or mana (adaptive)." />
  </Node>
  <Node name="w4v3">
    <Key key="Name" value="Killstreak Empowerment" />
    <Key key="Description" value="For each enemy killed, the character gains 0.2% (max 10%) attack power or spell power (adaptive). 50% of stacks are lost upon death." />
  </Node>
  <Node name="t1v1">
    <Key key="Name" value="Stalwart Defender" />
    <Key key="Description" value="When the character has less than 50% health, he receives 10 Armor and 10 Magic Resist." />
  </Node>
  <Node name="t1v2">
    <Key key="Name" value="Retaliatory Surge" />
    <Key key="Description" value="After entering combat, the hero will reflect 20% damage of next 5 incoming auto-attacks." />
  </Node>
  <Node name="t1v3">
    <Key key="Name" value="Battle-Hardened" />
    <Key key="Description" value="Every 2 seconds out of combat, the player gains 1 Armor and Magic Resist up to 10 stacks. Upon taking damage, the player loses 1 stack." />
  </Node>
  <Node name="t1v4">
    <Key key="Name" value="In the moment" />
    <Key key="Description" value="Increase {{EffectCreator.Effect.nm}}." />
    <Key key="Level" value="{{EffectCreator.Effect.nm}}: +{{EffectCreator.Effect.val}}" />
  </Node>
  <Node name="t1v5">
    <Key key="Name" value="Iron will" />
    <Key key="Description" value="Increase {{EffectCreator.Effect.nm}}." />
    <Key key="Level" value="{{EffectCreator.Effect.nm}}: +{{EffectCreator.Effect.val}}" />
  </Node>
  <Node name="t2v1">
    <Key key="Name" value="Shielded Defense" />
    <Key key="Description" value="Taking magic damage grants a magical shield for 10% characters maximum health. Taking physical damage grants a physical shield for 10% characters maximum health. Cooldown: 3 minute." />
  </Node>
  <Node name="t2v2">
    <Key key="Name" value="Protector's Presence" />
    <Key key="Description" value="Armor and Magic Resist are increased by 5 for each ally character nearby (20 meters) the character. Maximum of 3 stacks.&#xD;" />
  </Node>
  <Node name="t2v3">
    <Key key="Name" value="Menacing Aura" />
    <Key key="Description" value="For each enemy nearby (20m), the character gains 3 Armor and 3 Magic Resist, up to a maximum of 6 stacks." />
  </Node>
  <Node name="t2v4">
    <Key key="Name" value="Universal soldier" />
    <Key key="Description" value="Increase {{EffectCreator.Effect.nm}}." />
    <Key key="Level" value="{{EffectCreator.Effect.nm}}: +{{EffectCreator.Effect.val}}" />
  </Node>
  <Node name="t3v1">
    <Key key="Name" value="Bulwark" />
    <Key key="Description" value="All critical strikes dealt to the character have a reduced critical damage multiplier of 50%." />
  </Node>
  <Node name="t3v2">
    <Key key="Name" value="Bouncing Back" />
    <Key key="Description" value="After being critically struck, the character gains a buff that amplifies any incoming healing by 5% (max 30%). The effect lasts for 5 seconds." />
  </Node>
  <Node name="t3v3">
    <Key key="Name" value="Indomitable" />
    <Key key="Description" value="After being critically hit by an enemy, the character cannot receive critical hits for the next 5 seconds." />
  </Node>
  <Node name="t4v1">
    <Key key="Name" value="Juggernaut" />
    <Key key="Description" value="Increases character's maximum health by 10%." />
  </Node>
  <Node name="t4v2">
    <Key key="Name" value="Tenacity" />
    <Key key="Description" value="Reduces the duration of crowd control effects on the character by 30%    " />
  </Node>
  <Node name="t4v3">
    <Key key="Name" value="Vengeful Souls" />
    <Key key="Description" value="For each enemy killed, the character gains 0.2% (max 15%) maximum health. All stacks are lost upon death." />
  </Node>
  <Node name="m1v1">
    <Key key="Name" value="Emergency Rewind" />
    <Key key="Description" value="Reduces the cooldown of abilities by 10% when the character's health drops below 50%." />
  </Node>
  <Node name="m1v2">
    <Key key="Name" value="Mana Flow" />
    <Key key="Description" value="Increases the player's resource regeneration by 5% for each ability that is on cooldown." />
  </Node>
  <Node name="m1v3">
    <Key key="Name" value="Harmonic Trade-off" />
    <Key key="Description" value="Reduces resource cost of abilities by 10%." />
    <Key key="Level" value="&#xA;" />
  </Node>
  <Node name="m1v4">
    <Key key="Name" value="Expose" />
    <Key key="Description" value="Increase {{EffectCreator.Effect.nm}}." />
    <Key key="Level" value="{{EffectCreator.Effect.nm}}: +{{EffectCreator.Effect.val}}" />
  </Node>
  <Node name="m1v5">
    <Key key="Name" value="Open Mind" />
    <Key key="Description" value="Increase {{EffectCreator.Effect.nm}}." />
    <Key key="Level" value="{{EffectCreator.Effect.nm}}: +{{EffectCreator.Effect.val}}" />
  </Node>
  <Node name="m2v1">
    <Key key="Name" value="Arcane Insight" />
    <Key key="Description" value="Reduces the cooldown of all abilities by 20%." />
  </Node>
  <Node name="m2v2">
    <Key key="Name" value="Slaying Momentum" />
    <Key key="Description" value="After killing an enemy, abilities on cooldown are reduced by 1 second." />
  </Node>
  <Node name="m2v3">
    <Key key="Name" value="Vengeance of the Interrupted" />
    <Key key="Description" value="If the character's ability is interrupted, their next ability within 6 seconds will cost 0 resource." />
  </Node>
  <Node name="m2v4">
    <Key key="Name" value="Sleight of hand" />
    <Key key="Description" value="Increase {{EffectCreator.Effect.nm}}." />
    <Key key="Level" value="{{EffectCreator.Effect.nm}}: +{{EffectCreator.Effect.val}}" />
  </Node>
  <Node name="m3v1">
    <Key key="Name" value="Mindshatter Resistance" />
    <Key key="Description" value="Ability interruption effects have a 75% reduced duration on the character." />
  </Node>
  <Node name="m3v2">
    <Key key="Name" value="Aetheric Redirection" />
    <Key key="Description" value="10% of incoming damage is redirected to mana instead of health." />
  </Node>
  <Node name="m3v3">
    <Key key="Name" value="Mana Shield" />
    <Key key="Description" value="Gain a shield equal to 10% of maximum mana. The shield recharges after 10 seconds out of combat." />
  </Node>
  <Node name="m4v1">
    <Key key="Name" value="Maetheric Reservoir" />
    <Key key="Description" value="Increases character's maximum Mana by 10%." />
  </Node>
  <Node name="m4v2">
    <Key key="Name" value="Mana Siphon" />
    <Key key="Description" value="Damage dealing abilities restores 2% of the damage dealt as mana." />
  </Node>
  <Node name="m4v3">
    <Key key="Name" value="Concentrated Power" />
    <Key key="Description" value="If the character remains stationary for 3 seconds, their abilities damage is enhanced by 15%." />
  </Node>
  <Node name="as1v1">
    <Key key="Name" value="Lurking Precision" />
    <Key key="Description" value="Increases physical or magical critical strike chance (adaptive) by 1% every 10 seconds outside of combat. Maximum 50%. Works on first damage." />
  </Node>
  <Node name="as1v2">
    <Key key="Name" value="Shadow Dance" />
    <Key key="Description" value="After using a skill, the next auto-attack has an increased physical critical strike chance by 10%. Cooldown 2.5 seconds." />
  </Node>
  <Node name="as1v3">
    <Key key="Name" value="Shadow Strike" />
    <Key key="Description" value="After landing a critical strike, the character gains 10% physical or magical critical strike chance (adaptive) for 5 seconds." />
  </Node>
  <Node name="as1v4">
    <Key key="Name" value="Weakness spotter" />
    <Key key="Description" value="Increase {{EffectCreator.Effect.nm}}." />
    <Key key="Level" value="{{EffectCreator.Effect.nm}}: +{{EffectCreator.Effect.val}}" />
  </Node>
  <Node name="as1v5">
    <Key key="Name" value="Predator instinct" />
    <Key key="Description" value="Increase {{EffectCreator.Effect.nm}}." />
    <Key key="Level" value="{{EffectCreator.Effect.nm}}: +{{EffectCreator.Effect.val}}" />
  </Node>
  <Node name="as2v1">
    <Key key="Name" value="Bloodthirsty Edge" />
    <Key key="Description" value="Killing an enemy increases flat armor penetration or magic penetration (adaptive) by 10 for 10 seconds." />
  </Node>
  <Node name="as2v2">
    <Key key="Name" value="Piercing Onslaught" />
    <Key key="Description" value="The character gains a stacking buff when their ability deal damage to an enemy, granting 1 flat armor or magic penetration (adaptive) per stack (up to 10 stacks). Stacks last for 7 seconds." />
  </Node>
  <Node name="as2v3">
    <Key key="Name" value="Critical Affliction" />
    <Key key="Description" value="If the character deals critical damage to a target affected by their periodic damage effect, the next 3 ticks of that effect will also deal critical damage." />
  </Node>
  <Node name="as2v4">
    <Key key="Name" value="Perfect reflexes" />
    <Key key="Description" value="Cooldown Reduction decrease." />
    <Key key="Level" value="{{EffectCreator.Effect.nm}}: -{{EffectCreator.Effect.val}}" />
  </Node>
  <Node name="as3v1">
    <Key key="Name" value="Predator" />
    <Key key="Description" value="When the character attacks an enemy without allies nearby, they gain 10% armor or magic penetration (adaptive) and deal an additional 50% physical or magical critical damage power against this enemy (adaptive) for 5 seconds. Cooldown is 20 seconds." />
  </Node>
  <Node name="as3v2">
    <Key key="Name" value="Backstab" />
    <Key key="Description" value="The character gains 10% armor penetration or magic penetration (adaptive) and deals 50% additional physical or magical critical damage power (adaptive) to enemies when attacking them from behind." />
  </Node>
  <Node name="as3v3">
    <Key key="Name" value="Surprise Attack" />
    <Key key="Description" value="When the character disappears using camouflage or invisibility from the enemy's sight for 2 seconds during combat, their next ability or auto-attack gains an additional 30% physical or magical critical strike chance (adaptive)." />
  </Node>
  <Node name="as4v1">
    <Key key="Name" value="Ghostly Reflexes" />
    <Key key="Description" value="The character can notice every stealth activation within a 30-meter radius. Cooldown 30 seconds" />
  </Node>
  <Node name="as4v2">
    <Key key="Name" value="Giant Slayer" />
    <Key key="Description" value="If the character attacks an enemy with maximum health greater than the character's own (2x for monsters), the enemy receives 10% increased damage from the character." />
  </Node>
  <Node name="as4v3">
    <Key key="Name" value="Blade Fury" />
    <Key key="Description" value="When landing a critical strike, the character deals an additional 30% of the damage to surrounding enemies within 2.5 meters." />
  </Node>
  <Node name="ar1v1">
    <Key key="Name" value="Heroic Surge" />
    <Key key="Description" value="When the character's health drops below 50%, their attack speed is increased by 10%." />
  </Node>
  <Node name="ar1v2">
    <Key key="Name" value="Relentless Assault" />
    <Key key="Description" value="Auto-attacks against the same target increase the character's attack speed by 1% (stacking up to 10 times).The effect lasts for 3 seconds or fails if the character changes target." />
  </Node>
  <Node name="ar1v3">
    <Key key="Name" value="Swift Onslaught" />
    <Key key="Description" value="For 10 seconds after entering combat, the character gains 10% attack speed for 10 seconds." />
  </Node>
  <Node name="ar1v4">
    <Key key="Name" value="Nimble" />
    <Key key="Description" value="Increase {{EffectCreator.Effect.nm}}." />
    <Key key="Level" value="{{EffectCreator.Effect.nm}}: +{{EffectCreator.Effect.val}}" />
  </Node>
  <Node name="ar1v5">
    <Key key="Name" value="Sieve" />
    <Key key="Description" value="Increase {{EffectCreator.Effect.nm}}." />
    <Key key="Level" value="{{EffectCreator.Effect.nm}}: +{{EffectCreator.Effect.val}}" />
  </Node>
  <Node name="ar2v1">
    <Key key="Name" value="Feline Reflexes" />
    <Key key="Description" value="Increases movement speed by 7% for 5 seconds after using dash abilities." />
  </Node>
  <Node name="ar2v2">
    <Key key="Name" value="Leaps and Bounds" />
    <Key key="Description" value="After suffering movement-impairing effects, the character's movement speed is increased by 7% for 5 seconds." />
  </Node>
  <Node name="ar2v3">
    <Key key="Name" value="Unshackled" />
    <Key key="Description" value="Gain immunity to movement-impairing effects for 2 second after using a dash ability." />
  </Node>
  <Node name="ar2v4">
    <Key key="Name" value="Broad-minded" />
    <Key key="Description" value="Increase {{EffectCreator.Effect.nm}}." />
    <Key key="Level" value="{{EffectCreator.Effect.nm}}: +{{EffectCreator.Effect.val}}" />
  </Node>
  <Node name="ar3v1">
    <Key key="Name" value="Explorer's Instinct" />
    <Key key="Description" value="Grants the character a stacking 1% movement speed buff for every 10 seconds out of combat, up to a maximum of 5%." />
  </Node>
  <Node name="ar3v2">
    <Key key="Name" value="Predator's Vigor" />
    <Key key="Description" value="The character can sense wounded targets below 30% health within a large radius. Does not sense targets within a 20-meter radius. Activates once every 3 minutes." />
  </Node>
  <Node name="ar3v3">
    <Key key="Name" value="Escape Artist" />
    <Key key="Description" value="If the character's health drops below 15%, all immobilization effects are removed. Cooldown is 60 seconds." />
  </Node>
  <Node name="ar4v1">
    <Key key="Name" value="Surge of Speed" />
    <Key key="Description" value="If the character takes damage exceeding 30% of their maximum health within 3 seconds, their attack speed increases by 20% for 10 seconds." />
  </Node>
  <Node name="ar4v2">
    <Key key="Name" value="Small But Mighty" />
    <Key key="Description" value="If the character attacks an enemy with maximum health greater than the character's own (2x for monsters), the character gains a 15% increase in attack speed against this target." />
  </Node>
  <Node name="ar4v3">
    <Key key="Name" value="Thrill of the Hunt" />
    <Key key="Description" value="For each enemy killed, the character gains 0.2% (max 10%) attack speed. 50% of stacks are lost upon death." />
  </Node>
  <Node name="h1v1">
    <Key key="Name" value="Luminescent Grace" />
    <Key key="Description" value="Increases healing and shielding effectiveness by 10% when the character's mana is above 80%." />
  </Node>
  <Node name="h1v2">
    <Key key="Name" value="Serene Respite" />
    <Key key="Description" value="If the character has not used any healing or shielding abilities for 10 seconds, their next healing or shielding ability will be 3% stronger up to 15%." />
  </Node>
  <Node name="h1v3">
    <Key key="Name" value="Harmonic Trade-off" />
    <Key key="Description" value="Increases healing and shielding by 10%, but reduces damage by 10%." />
  </Node>
  <Node name="h1v4">
    <Key key="Name" value="Healer's hunch" />
    <Key key="Description" value="Increase {{EffectCreator.Effect.nm}}." />
    <Key key="Level" value="{{EffectCreator.Effect.nm}}: +{{EffectCreator.Effect.val}}" />
  </Node>
  <Node name="h1v5">
    <Key key="Name" value="Accelerated Rehabilitation" />
    <Key key="Description" value="Increase {{EffectCreator.Effect.nm}}." />
    <Key key="Level" value="{{EffectCreator.Effect.nm}}: +{{EffectCreator.Effect.val}}" />
  </Node>
  <Node name="h2v1">
    <Key key="Name" value="Symbiotic Mending" />
    <Key key="Description" value="Healing a target also heals the character for 10% of the amount healed" />
  </Node>
  <Node name="h2v2">
    <Key key="Name" value="Critical Attunement" />
    <Key key="Description" value="Critical healing applies a healing-over-time effect to a target for 10 seconds, equivalent to 10% of the amount healed" />
  </Node>
  <Node name="h2v3">
    <Key key="Name" value="Aegis Retribution" />
    <Key key="Description" value="Critical healing applies a shield to a target for 10 seconds, equivalent to 10% of the amount healed." />
  </Node>
  <Node name="h2v4">
    <Key key="Name" value="Doctor's ardor" />
    <Key key="Description" value="Increase {{EffectCreator.Effect.nm}}." />
    <Key key="Level" value="{{EffectCreator.Effect.nm}}: +{{EffectCreator.Effect.val}}" />
  </Node>
  <Node name="h3v1">
    <Key key="Name" value="Purifying Rejuvenation" />
    <Key key="Description" value="When removing a negative effect, restores 10% of the missing health to the target over 5 seconds." />
  </Node>
  <Node name="h3v2">
    <Key key="Name" value="Benevolent Echoes" />
    <Key key="Description" value="Increases healing and shielding by 4% for every unique target healed or shielded within the last 10 seconds (max 12%)." />
  </Node>
  <Node name="h3v3">
    <Key key="Name" value="Cleansing Touch" />
    <Key key="Description" value="Remove a negative effect from a nearby ally with the lowest health. Cooldown 60 seconds." />
  </Node>
  <Node name="h4v1">
    <Key key="Name" value="Chrono-Fortification" />
    <Key key="Description" value="The duration of shields applied by the hero is doubled." />
  </Node>
  <Node name="h4v2">
    <Key key="Name" value="Overflowing Barrier" />
    <Key key="Description" value="20% of the hero's overhealing becomes a shield (maximum shield strength is equal to 10% of the target's maximum health) for 10 seconds." />
  </Node>
  <Node name="h4v3">
    <Key key="Name" value="Shield Master" />
    <Key key="Description" value="The player's shield-applying abilities now have 2 charges." />
  </Node>
  <Node name="f1v1">
    <Key key="Description" value="Increase {{EffectCreator.Effect.nm}}." />
    <Key key="Level" value="{{EffectCreator.Effect.nm}}: +{{EffectCreator.Effect.val}}" />
  </Node>
  <Node name="Not_enough_talent">
    <Key key="Key" value="Not enough talent points" />
  </Node>
  <Node name="Archer" />
  <Node name="Farmer" />
  <Node name="Healer" />
  <Node name="w5v1">
    <Key key="Name" value="Charge Catalyst" />
    <Key key="Description" value="For each ability used by the character, allies, or enemies within a radius of 10 meters, the character gains charges for 5 seconds. At 10 charges, the next ability will deal 20% more damage." />
  </Node>
  <Node name="w5v2">
    <Key key="Name" value="True Strike" />
    <Key key="Description" value="Every third basic attack deals an additional 3% of the target's current health as true damage." />
  </Node>
  <Node name="w5v3">
    <Key key="Name" value="Bloodthirst" />
    <Key key="Description" value="The character gains an additional 1% attack power or spell power (adaptive) for every 3% of their missing health." />
  </Node>
  <Node name="w6v1">
    <Key key="Name" value="Battle-bound" />
    <Key key="Description" value="Auto-attack or targeted ability slows down the target." />
    <Key key="Level" value="Move speed: -30%&#xD;&#xA;Duration: 3 sec&#xD;&#xA;Cooldown: 15 sec" />
  </Node>
  <Node name="w6v2">
    <Key key="Name" value="Killing machine" />
    <Key key="Description" value="The less your Health, the more outgoing Physical damage." />
    <Key key="Level" value="Health values: 80% 50% 20%&#xD;&#xA;Physical damage: +5% +10% +25%" />
  </Node>
  <Node name="Assassin" />
  <Node name="Pathfinder" />
  <Node name="m5v1">
    <Key key="Name" value="Temporal Rupture" />
    <Key key="Description" value="Effects that deal periodic damage do not apply periodic damage. Instead, they deal 130% of the total damage to the target when the effect duration ends." />
  </Node>
  <Node name="p2v4">
    <Key key="Name" value="Natural selection" />
    <Key key="Description" value="Increase {{EffectCreator.Effect.nm}}." />
    <Key key="Level" value="{{EffectCreator.Effect.nm}}: +{{EffectCreator.Effect.val}}" />
  </Node>
  <Node name="m5v2">
    <Key key="Name" value="Chrono Cascade" />
    <Key key="Description" value="After using an ability, reduce the remaining cooldown on your other abilities by 1 second." />
  </Node>
  <Node name="m5v3">
    <Key key="Name" value="Focused Assault" />
    <Key key="Description" value="&#xD;Each character's damaging ability used on the same target increases the damage of the next ability used on that same target by 5%. The effect stacks up to 5 times and lasts for 7 seconds. If an ability is used on a different target, the buff expires." />
  </Node>
  <Node name="m6v1">
    <Key key="Name" value="Burden of Power" />
    <Key key="Description" value="Increase of Abilities Damage for longer Cooldown reduction." />
    <Key key="Level" value="Cooldown reduction: -20%&#xD;&#xA;Abilities Damage : +10%" />
  </Node>
  <Node name="m6v2">
    <Key key="Name" value="Wallow in Magic" />
    <Key key="Description" value="Using of ability applies the Effect that increases all Damage." />
    <Key key="Level" value="Damage: +5%&#xD;&#xA;Duration: 5 sec&#xD;&#xA;Cooldown: 15 sec" />
  </Node>
  <Node name="as5v1">
    <Key key="Name" value="Critstacker" />
    <Key key="Description" value="Non-critical auto-attacks grant a buff that increases the chance of physical or magical critical strike (adaptive) by 1% for 5 seconds, which are consumed upon landing a critical strike. The effect can stack up to 100%." />
  </Node>
  <Node name="as5v2">
    <Key key="Name" value="Blade Master" />
    <Key key="Description" value="When the character scores a critical hit, they gain a stack of Blade Master. At 5 stacks, their next ability deals 20% increased damage and consumes all stacks." />
  </Node>
  <Node name="as5v3">
    <Key key="Name" value="Disruptive Strike" />
    <Key key="Description" value="Enemy can not use dash abilities for 3 seconds after player deals damage that exceeds 30% of the enemy's maximum health within 5 seconds." />
  </Node>
  <Node name="as6v1">
    <Key key="Name" value="Dead zone" />
    <Key key="Description" value="Increase of all damage to the enemy's back." />
    <Key key="Level" value="Damage +5%" />
  </Node>
  <Node name="as6v2">
    <Key key="Name" value="Ashes to ashes" />
    <Key key="Description" value="Auto-Attack Damage to the enemy with Health less then 10% of Health Maximum increases damage of your next Ability." />
    <Key key="Level" value="Ability Damage: +10%&#xD;&#xA;Duration: 5 sec" />
  </Node>
  <Node name="f1v5" />
  <Node name="f4v1">
    <Key key="Name" value="Increased resources drop" />
    <Key key="Description" value="Increase {{EffectCreator.Effect.nm}}." />
    <Key key="Level" value="{{EffectCreator.Effect.nm}}: +{{EffectCreator.Effect.val}}" />
  </Node>
  <Node name="f2v4" />
  <Node name="p3v1">
    <Key key="Name" value="Cozy Campfires" />
    <Key key="Description" value="All campfires have an invisibility detection effect within a 15-meter radius." />
  </Node>
  <Node name="p4v1">
    <Key key="Name" value="Desperate Escape" />
    <Key key="Description" value="If the character's health drops below 15%, the hero becomes invisible for 1.5 seconds. Can only activate once every 60 seconds." />
  </Node>
  <Node name="S1C_first">
    <Key key="Name" value="Boost Attack Power" />
    <Key key="Description" value="Increases Attack Power" />
  </Node>
  <Node name="S1C_second">
    <Key key="Name" value="Boost Strength" />
    <Key key="Description" value="Increases Strength" />
  </Node>
  <Node name="CHA_S1_Q1">
    <Key key="Name" value="CHA_S1_Q1" />
    <Key key="Description" value="Усиливает эффект способности Q на 5/10/15%" />
  </Node>
  <Node name="CHA_S1_P1">
    <Key key="Name" value="CHA_S1_P1" />
    <Key key="Description" value="Чемпион получает до 30% доп силы атаки, если у него малое количество ХП (меньше 50% от максимального значения)" />
  </Node>
  <Node name="CHA_S1_E1">
    <Key key="Name" value="CHA_S1_E1" />
    <Key key="Description" value="Усиливает эффект способности E на 5/10/15%" />
  </Node>
  <Node name="CHA_S1_E2">
    <Key key="Name" value="CHA_S1_E2" />
    <Key key="Description" value="Increase {{EffectCreator.Effect.nm}}" />
    <Key key="Level" value="{{EffectCreator.Effect.nm}}: +{{EffectCreator.Effect.val}}" />
  </Node>
  <Node name="CHA_S1_W1">
    <Key key="Name" value="CHA_S1_W1" />
    <Key key="Description" value="Увеличивает ширину области поражения способности &quot;Бросок Кинжала&quot; на 0.1 метр." />
  </Node>
  <Node name="CHA_S1_W2">
    <Key key="Name" value="CHA_S1_W2" />
    <Key key="Description" value="Пораженный противник замедляется на 10%/20%/30%." />
  </Node>
  <Node name="CHA_S1_W3">
    <Key key="Name" value="CHA_S1_W3" />
    <Key key="Description" value="Увеличивает базовый урон способности &quot;Бросок Кинжала&quot; на 60 единиц." />
  </Node>
  <Node name="CHA_S1_W4">
    <Key key="Name" value="CHA_S1_W4" />
    <Key key="Description" value="Получает два стака пассивки если попадает способностью." />
  </Node>
  <Node name="CHA_S1_Q2">
    <Key key="Name" value="CHA_S1_Q2" />
    <Key key="Description" value="Если способность поразила 3 цели, то Чемпион получает Бафф на усиление урона +30% на следующую способность q. Время Баффа 12 сек или по условию" />
  </Node>
  <Node name="CHA_S1_W7">
    <Key key="Name" value="CHA_S1_W7" />
    <Key key="Description" value="Увеличение урона способности W на 5%/10%/15%" />
  </Node>
  <Node name="CHA_S1_E3">
    <Key key="Name" value="CHA_S1_E3" />
    <Key key="Description" value="Увеличение длительности способности на 1/2/3 сек." />
  </Node>
  <Node name="CHA_S1_R2">
    <Key key="Name" value="CHA_S1_R2" />
    <Key key="Description" value="Увеличение дальности применения способности на 0.5/1/1.5 метра" />
  </Node>
  <Node name="CHA_S1_W6">
    <Key key="Name" value="CHA_S1_W6" />
    <Key key="Description" value="Увеличение радиуса работы способности на 0.25/0.5/0.75 метра" />
  </Node>
  <Node name="CHA_S1_E4">
    <Key key="Name" value="CHA_S1_E4" />
    <Key key="Description" value="Усиливает эффект баффа на 5%/10% от максимального здоровья Чемпиона." />
  </Node>
  <Node name="CHA_S1_R3">
    <Key key="Name" value="CHA_S1_R3" />
    <Key key="Description" value="Увеличивает ширину зоны притягивания (прямоугольник) x+0,5, x +1, x+ 1,5" />
  </Node>
  <Node name="CHA_S1_Q4">
    <Key key="Name" value="CHA_S1_Q4" />
    <Key key="Description" value="Увеличивает угол поражения способности" />
  </Node>
  <Node name="CHA_S1_Q3">
    <Key key="Name" value="CHA_S1_Q3" />
    <Key key="Description" value="При нанесении урона по нескольким целям способность откатывается быстрее на 0.5 секунды за каждую пораженную цель (макс 3 сек)" />
  </Node>
  <Node name="CHA_S1_R1">
    <Key key="Name" value="CHA_S1_R1" />
    <Key key="Description" value="Если Чемпион задевает противника способностью, то он получает бафф на одну автоатаку - часть урона следующей автоатаки нанесется в небольшое аое вокруг цели(сплэш). Чемпион получает по одному стаку баффа за каждую задетую цель. каждая автоатака будет снимать один стак." />
  </Node>
  <Node name="CHA_S1_W5">
    <Key key="Name" value="CHA_S1_W5" />
    <Key key="Description" value="Вихрь смерти замедляет противника на 10%. &#xD;&#xA;" />
  </Node>
  <Node name="CHA_S2_P1">
    <Key key="Name" value="CHA_S2_P1" />
    <Key key="Description" value="Пассивка приобретает дополнительный стак" />
  </Node>
  <Node name="CHA_S2_G1">
    <Key key="Name" value="CHA_S2_G1" />
    <Key key="Description" value="Пассивно увеличивает скорость атаки на 3%/6%/9%" />
  </Node>
  <Node name="CHA_S2_W1">
    <Key key="Name" value="CHA_S2_W1" />
    <Key key="Description" value="Также аое оставляет воид зону, которая вешает на противников замедление и наносит урон в теч 5 сек." />
  </Node>
  <Node name="CHA_S2_R1">
    <Key key="Name" value="CHA_S2_R1" />
    <Key key="Description" value="В течение времени метки, на цели можно стакать пассивку больше 3х стаков, без ограничений. По окончанию действия метки на цели нельзя стакать пассивку, пока не спадет старая (с большими стаками)" />
  </Node>
  <Node name="CHA_S2_R2">
    <Key key="Name" value="CHA_S2_R2" />
    <Key key="Description" value="Метка подсвечивает противника в тумане войны" />
  </Node>
  <Node name="CHA_S2_R3">
    <Key key="Name" value="CHA_S2_R3" />
    <Key key="Description" value="Автоатаки по противнику под меткой дают Чемпиону кратковременный бафф на скорость передвижения на 1/1.5/2 сек" />
  </Node>
  <Node name="CHA_S2_R4">
    <Key key="Name" value="CHA_S2_R4" />
    <Key key="Description" value="Увеличивает длительность эффекта понижения брони" />
  </Node>
  <Node name="CHA_S2_E1">
    <Key key="Name" value="CHA_S2_E1" />
    <Key key="Description" value="Переключение стоек дает Чемпиону кратковременный бафф на маг резист, армор и скорость передвижения. " />
  </Node>
  <Node name="CHA_S2_E2">
    <Key key="Name" value="CHA_S2_E2" />
    <Key key="Description" value="Усиливает селфбафф на скорость передвижения и резисты&#xA;" />
  </Node>
  <Node name="CHA_S2_Q1">
    <Key key="Name" value="CHA_S2_Q1" />
    <Key key="Description" value="Увеличивает длительность рута" />
  </Node>
  <Node name="CHA_S2_Q2">
    <Key key="Name" value="CHA_S2_Q2" />
    <Key key="Description" value="Способность также наносит урон и рутает противников в АОЕ вокруг цели. Зона поражения аое меньше чем у w способности в 1,5 раза." />
  </Node>
  <Node name="CHA_S2_Q3">
    <Key key="Name" value="CHA_S2_Q3" />
    <Key key="Description" value="Увеличение урона способности на 5%/10%/15%" />
  </Node>
  <Node name="CHA_S2_Q4">
    <Key key="Name" value="CHA_S2_Q4" />
    <Key key="Description" value="Понижает кд способности на 1/2/3 сек" />
  </Node>
  <Node name="CHA_S2_W2">
    <Key key="Name" value="CHA_S2_W2" />
    <Key key="Description" value="Способность дополнительно накладывает кровотечение." />
  </Node>
  <Node name="CHA_S2_W3">
    <Key key="Name" value="CHA_S2_W3" />
    <Key key="Description" value="Увеличивает дальность применения способности" />
  </Node>
  <Node name="CHA_S2_W4">
    <Key key="Name" value="CHA_S2_W4" />
    <Key key="Description" value="Усиление эффекта замедления на 10%/20%/30%" />
  </Node>
  <Node name="CHA_S2_W5">
    <Key key="Name" value="CHA_S2_W5" />
    <Key key="Description" value="Увеличение радиуса поражения способности" />
  </Node>
  <Node name="CHA_S2_W6">
    <Key key="Name" value="CHA_S2_W6" />
    <Key key="Description" value="Увеличивает длительность воид зоны на 1/2/3 сек" />
  </Node>
  <Node name="CHA_S2_E3">
    <Key key="Name" value="CHA_S2_E3" />
    <Key key="Description" value="Увеличивает урон по доп целям во 2-й стойке на 5%/10%/15%&#xA;" />
  </Node>
  <Node name="ORC_S1_R1" />
  <Node name="s1v1">
    <Key key="Name" value="Aura of Ferocity" />
    <Key key="Description" value="Increases the outgoing damage of character and nearby allies by 5%. (Works only if allies are nearby)." />
  </Node>
  <Node name="p1v1">
    <Key key="Name" value="Wanderer's Resolve" />
    <Key key="Description" value="The character gains 5% damage reduction when no allies are nearby." />
  </Node>
  <Node name="p1v2">
    <Key key="Name" value="Self-Sustenance" />
    <Key key="Description" value="If there are no allies nearby, the character receives health regeneration equal to 0.5% of their maximum health per second for 20 seconds after exiting combat." />
  </Node>
  <Node name="p2v1">
    <Key key="Name" value="Rejuvenating Essence" />
    <Key key="Description" value="Healing and resource restoration received from consumables is increased by 20%, and their cooldown is reduced by 20%." />
  </Node>
  <Node name="p2v2">
    <Key key="Name" value="Resourceful Explorer" />
    <Key key="Description" value="Upon killing an enemy, the character restores 3% of their maximum health and mana." />
  </Node>
  <Node name="p2v3">
    <Key key="Name" value="Eldritch Transmutation" />
    <Key key="Description" value="When using a alchemy consumables, gain a 10% damage boost and 10% damage reduction for 10 seconds." />
  </Node>
  <Node name="p1v3">
    <Key key="Name" value="Lone Wolf" />
    <Key key="Description" value="When there are no allied character nearby, the character gains 5% increased damage." />
  </Node>
  <Node name="p1v4">
    <Key key="Name" value="Scar by scar" />
    <Key key="Description" value="Increase {{EffectCreator.Effect.nm}}." />
    <Key key="Level" value="{{EffectCreator.Effect.nm}}: +{{EffectCreator.Effect.val}}" />
  </Node>
  <Node name="p1v5">
    <Key key="Name" value="Always in shape" />
    <Key key="Description" value="Increase {{EffectCreator.Effect.Effects.0.nm}}, {{EffectCreator.Effect.Effects.1.nm}} and {{EffectCreator.Effect.Effects.2.nm}}." />
    <Key key="Level" value="{{EffectCreator.Effect.Effects.0.nm}}: +{{EffectCreator.Effect.Effects.0.val}}&#xA;{{EffectCreator.Effect.Effects.1.nm}}: +{{EffectCreator.Effect.Effects.1.val}}&#xA;{{EffectCreator.Effect.Effects.2.nm}}: +{{EffectCreator.Effect.Effects.2.val}}" />
  </Node>
  <Node name="p3v2">
    <Key key="Name" value="Flame Forged" />
    <Key key="Description" value="After using a &quot;campfire,&quot; the character receives a buff that increases the character's primary attribute by 10% (adaptive) for 5 minutes." />
  </Node>
  <Node name="p3v3">
    <Key key="Name" value="Firestarter" />
    <Key key="Description" value="Create campfires with just two pieces of magic wood and no matches." />
  </Node>
  <Node name="p4v2">
    <Key key="Name" value="Sneak Prevention" />
    <Key key="Description" value="The character cannot be approached unnoticed, therefore all effects of attacks from behind and from invisibility do not work." />
  </Node>
  <Node name="p4v3">
    <Key key="Name" value="Slow and Steady" />
    <Key key="Description" value="Able to detect wards. Activates once every 30 seconds." />
  </Node>
  <Node name="p5v1">
    <Key key="Name" value="Guardian of the Wild" />
    <Key key="Description" value="Upon taking lethal damage, the character survives at 1 hp and granted a shield equal to 30% of their maximum health for 10 seconds. This effect can only occur once every 5 minutes." />
  </Node>
  <Node name="p5v2">
    <Key key="Name" value="Solo Survivor's Hunger" />
    <Key key="Description" value="When there are no allies nearby and the character's health drops below 80%/50%/20%, they gain +3/6/9% vampirism." />
  </Node>
  <Node name="p5v3">
    <Key key="Name" value="Duration Enhancement System" />
    <Key key="Description" value="All positive effects 1 minute duration or more on the character stronger by 20% and last 40% longer." />
  </Node>
  <Node name="p6v2">
    <Key key="Name" value="Stay alive" />
    <Key key="Description" value="Когда Здоровье опускается ниже 10% , Скорость передвижения увеличивается." />
    <Key key="Level" value="Скорость передвижения: + 20%" />
  </Node>
  <Node name="p6v1">
    <Key key="Name" value="Sixth sense" />
    <Key key="Description" value="После 10 сек неподвижности на миникарте появляются отметки игроков и монстров." />
    <Key key="Level" value="Радиус действия : 25м&#xD;&#xA;Время действия: 5 сек&#xD;&#xA;Повторное использование: 10 сек" />
  </Node>
  <Node name="s2v1">
    <Key key="Name" value="Energized Bastion" />
    <Key key="Description" value="Shields applied by the character grant the target 10% Attack Speed for the shield's duration." />
  </Node>
  <Node name="s1v5">
    <Key key="Name" value="Just Whatever" />
    <Key key="Description" value="Increase {{EffectCreator.Effect.nm}}." />
    <Key key="Level" value="{{EffectCreator.Effect.nm}}: +{{EffectCreator.Effect.val}}" />
  </Node>
  <Node name="s1v2">
    <Key key="Name" value="Warden's Protection" />
    <Key key="Description" value="Character and nearby allies receive 5% reduced damage from all sources. (Works only if allies are nearby)." />
  </Node>
  <Node name="s1v3">
    <Key key="Name" value="Empowering Presence" />
    <Key key="Description" value="Character and nearby allies receive 5% movement speed. (Works only if allies are nearby). " />
  </Node>
  <Node name="s1v4">
    <Key key="Name" value="Censor's enemy" />
    <Key key="Description" value="Increase {{EffectCreator.Effect.nm}}." />
    <Key key="Level" value="{{EffectCreator.Effect.nm}}: +{{EffectCreator.Effect.val}}" />
  </Node>
  <Node name="s2v2">
    <Key key="Name" value="Dynamic Fortress" />
    <Key key="Description" value="Shields applied by the character grant the target 15 Armor (Bonus) or Magic Resist (Bonus)  (adaptive) for the shield's duration." />
  </Node>
  <Node name="s2v3">
    <Key key="Name" value="Mana Savior" />
    <Key key="Description" value="If the character interrupts an enemy's ability, restores 5% maximum Mana to the ally with the lowest mana level." />
  </Node>
  <Node name="s2v4">
    <Key key="Name" value="99 bottles on the wall" />
    <Key key="Description" value="Increase {{EffectCreator.Effect.nm}}." />
    <Key key="Level" value="{{EffectCreator.Effect.nm}}: +{{EffectCreator.Effect.val}}" />
  </Node>
  <Node name="s3v1">
    <Key key="Name" value="Coordinated Assault Tactic" />
    <Key key="Description" value="Character's abilities apply a charge to the target. Upon reaching 3 charges, an auto-attack from an ally against the target will stun it for 2 second." />
  </Node>
  <Node name="s3v2">
    <Key key="Name" value="Hard Control Expert" />
    <Key key="Description" value="When the character hits a target with hard crowd control, after the effect expires, the target gets marked. An auto-attack from an ally against the marked target will heal the ally for 5% of their maximum Health." />
  </Node>
  <Node name="s3v3">
    <Key key="Name" value="Weakening Curse" />
    <Key key="Description" value="Enemies affected by the character's movement-impairing abilities deal 15% reduced damage for the duration of the effect." />
  </Node>
  <Node name="s4v1">
    <Key key="Name" value="Sentinel's Embrace" />
    <Key key="Description" value="Grant character and nearby allies a 10% increase to their primary attribute. (Works only if allies are nearby)." />
  </Node>
  <Node name="s4v2">
    <Key key="Name" value="Amplified Efficiency Matrix" />
    <Key key="Description" value="All positive effects applied by the character with a duration of 1 minute or more become 15% stronger." />
  </Node>
  <Node name="s4v3">
    <Key key="Name" value="Insight" />
    <Key key="Description" value="The player's wards last twice as long and reveal 50% more of the fog of war." />
  </Node>
  <Node name="s5v1">
    <Key key="Name" value="Amplify Weakness" />
    <Key key="Description" value="Damaging abilities apply a mark to enemies for 5 seconds, increasing their damage taken from all allies by 10%." />
  </Node>
  <Node name="s5v2">
    <Key key="Name" value="Mark of Vampirism" />
    <Key key="Description" value="Direct damage abilities apply a mark to the enemy for 5 seconds. Damage dealt to the marked target grants the hero's allies vampirism equal to 5% of the damage dealt." />
  </Node>
  <Node name="s5v3">
    <Key key="Name" value="Radiant Ascension" />
    <Key key="Description" value="Using the ultimate ability grants character and nearby allies invulnerability for 2 second. (Works only if allies are nearby)." />
  </Node>
  <Node name="s6v1">
    <Key key="Name" value="Punks don't die" />
    <Key key="Description" value="Аура повышающая параметры Сопротивление Физическому Урону и Сопротивление Магическому Урону у союзников." />
    <Key key="Level" value="Сопротивление Физическому Урону: +10%&#xA;Сопротивление Магическому Урону: +10%" />
  </Node>
  <Node name="s6v2">
    <Key key="Name" value="On the verge of glory" />
    <Key key="Description" value=" Нахождение игрока на одном месте в течении 10 секунд оставляют на невидимом юните Ауру (для всех), увеличивающую мейн стат на 10%. Если мейн статы равны, то рандом. Юнит живет 10сек. Cd = 20 сек" />
  </Node>
  <Node name="Mage" />
  <Node name="s2v1Слово мое сталь">
    <Key key="Name" value="My words are steel" />
    <Key key="Description" value="Increase {{EffectCreator.Effect.nm}}." />
    <Key key="Level" value="{{EffectCreator.Effect.nm}}: +{{EffectCreator.Effect.val}}" />
  </Node>
  <Node name="ar5v1">
    <Key key="Name" value="Sniper's Precision" />
    <Key key="Description" value="Increases damage depending on the distance to the target. Damage is increased by 1% for each unit, starting from 4 meters away." />
  </Node>
  <Node name="ar6v1">
    <Key key="Name" value="Ace in the hole" />
    <Key key="Description" value="Using Auto-Attacks or Abilities apply an Effect that increases Physical Damage." />
    <Key key="Level" value="Physical Damage: +15%&#xA;Duration: 5 sec&#xA;Cooldown: 20 sec" />
  </Node>
  <Node name="ar5v2">
    <Key key="Name" value="Reach Mastery" />
    <Key key="Description" value="For each skill used, the character gains charges. Upon reaching 5 charges, the next skill will gain 3 meters to its range of application." />
  </Node>
  <Node name="ar5v3">
    <Key key="Name" value="Stationary Marksman" />
    <Key key="Description" value="For each skill used, the character gains charges. Upon reaching 5 charges, the next skill will gain 3 meters to its range." />
  </Node>
  <Node name="TalentPoints">
    <Key key="Key" value="{value1} Talent Points" />
  </Node>
  <Node name="CHA_S1_T_1">
    <Key key="Name" value="Ronin's Stoicism" />
    <Key key="Description" value="During the ability's duration, the Destroyer takes &lt;w&gt;20%&lt;/w&gt; less damage." />
  </Node>
  <Node name="CHA_S1_Q_1">
    <Key key="Name" value="Disrupting Blow" />
    <Key key="Description" value="When hit, the skill interrupts the cast." />
    <Key key="Level" value="+0.2 meter to Charge distance." />
  </Node>
  <Node name="CHA_S1_Q_2">
    <Key key="Name" value="Hamstring Cut" />
    <Key key="Description" value="Enemies affected by the ability experience a &lt;w&gt;20%&lt;/w&gt; slowing effect." />
    <Key key="Level" value="+0.2 meter to Charge distance." />
  </Node>
  <Node name="CHA_S1_Q_3">
    <Key key="Name" value="Health Shatterer" />
    <Key key="Description" value="The ability deals &lt;w&gt;25%&lt;/w&gt; more damage to enemies with full HPMax." />
  </Node>
  <Node name="CHA_S1_Q_4">
    <Key key="Name" value="Accumulating Power" />
    <Key key="Description" value="For each target hit by the ability, the next attack of the Destroyer increases by &lt;w&gt;10%&lt;/w&gt;. (Maximum &lt;w&gt;40%&lt;/w&gt;)." />
  </Node>
  <Node name="CHA_S1_Q_5">
    <Key key="Name" value="Quick Reprisal" />
    <Key key="Description" value="If the Destroyer hits an opponent, the ability can be reused within 2 seconds. It performs a short lunge forward, dealing &lt;pd&gt;physical damage&lt;/pd&gt; (&lt;w&gt;100%&lt;/w&gt; AttackPower) in front of the character." />
  </Node>
  <Node name="CHA_S1_T_2">
    <Key key="Name" value="Unbound Mobility" />
    <Key key="Description" value="During the ability's duration, the Destroyer gains &lt;w&gt;50%&lt;/w&gt; ressistance to slowing effects." />
  </Node>
  <Node name="CHA_S1_T_3">
    <Key key="Name" value="Sudden Death" />
    <Key key="Description" value="For each target hit by the ability, the Destroyer gains &lt;w&gt;+10%&lt;/w&gt; MoveSpeedFinalKPositive." />
  </Node>
  <Node name="CHA_S1_T_4">
    <Key key="Name" value="Armor Grinder" />
    <Key key="Description" value="Enemies damaged by the ability lose &lt;w&gt;5%&lt;/w&gt; Armor for &lt;w&gt;3&lt;/w&gt; seconds. The effect can stack up to 6 times." />
  </Node>
  <Node name="CHA_S1_T_5">
    <Key key="Name" value="Whirling Booster" />
    <Key key="Description" value="Increases the duration of the ability by &lt;w&gt;3&lt;/w&gt; seconds." />
  </Node>
  <Node name="CHA_S1_W_1">
    <Key key="Name" value="Chargedrive" />
    <Key key="Description" value="For each opponent hit by the ability, the Destroyer gains a charge for the passive skill (up to a maximum of &lt;w&gt;3&lt;/w&gt; charges per strike)." />
    <Key key="Level" value="+2% to damage in the outer radius zone.&#xA;" />
  </Node>
  <Node name="CHA_S1_W_2">
    <Key key="Name" value="Timecut" />
    <Key key="Description" value="For each opponent hit, the ability's cooldown is reduced by &lt;w&gt;1&lt;/w&gt; second (maximum reduction - &lt;w&gt;3&lt;/w&gt; seconds per single use of the ability)." />
    <Key key="Level" value="+2% to damage in the outer radius zone." />
  </Node>
  <Node name="CHA_S1_W_3">
    <Key key="Name" value="Epicenter" />
    <Key key="Description" value="Opponents in the center of the area will be stunned for &lt;w&gt;2&lt;/w&gt; seconds." />
  </Node>
  <Node name="CHA_S1_W_4">
    <Key key="Name" value="Cure Edge" />
    <Key key="Description" value="The Destroyer restores HPMax equal to &lt;w&gt;10%&lt;/w&gt; of the damage dealt when hitting opponents on the edge of the area of effect." />
    <Key key="Level" value="+2% to damage in the outer radius zone." />
  </Node>
  <Node name="CHA_S1_W_5">
    <Key key="Name" value="Blade Throw" />
    <Key key="Description" value="If the ability hits an enemy, it can be used again within &lt;w&gt;2&lt;/w&gt; seconds. The Destroyer throws their weapon in the chosen direction, dealing &lt;pd&gt;physical damage&lt;/pd&gt; (&lt;w&gt;100%&lt;/w&gt; AttackPower) to the first enemy hit." />
  </Node>
  <Node name="CHA_S1_E_1">
    <Key key="Name" value="Endless Empowerment" />
    <Key key="Description" value="Increases the duration of the buff by &lt;w&gt;5&lt;/w&gt; seconds." />
  </Node>
  <Node name="CHA_S1_E_2">
    <Key key="Name" value="Self-сonfidence" />
    <Key key="Description" value="Increases the bonus AttackPower and bonus HPMax gained by &lt;w&gt;5%&lt;/w&gt;." />
  </Node>
  <Node name="CHA_S1_E_3">
    <Key key="Name" value="Thunderous Roar" />
    <Key key="Description" value="The ability becomes AoE: In the area of effect, enemies lose &lt;w&gt;15%&lt;/w&gt; Armor and &lt;w&gt;15%&lt;/w&gt; Resist." />
  </Node>
  <Node name="CHA_S1_E_4">
    <Key key="Name" value="Commanding Shout" />
    <Key key="Description" value="The Destroyer becomes enraged and gains &lt;w&gt;10%&lt;/w&gt; resistance to crowd control effects." />
  </Node>
  <Node name="CHA_S1_E_5">
    <Key key="Name" value="Unchained" />
    <Key key="Description" value="Removes all slowing effects. Nearby allies also gain the enhancement effects." />
  </Node>
  <Node name="CHA_S1_R_1">
    <Key key="Name" value="Shockwave Recoil" />
    <Key key="Description" value="After landing, all enemies within &lt;w&gt;2&lt;/w&gt; meters outside of the damage radius are knocked back and Destroyer receives &lt;w&gt;50%&lt;/w&gt; SlowResistance for &lt;w&gt;3&lt;/w&gt; seconds." />
  </Node>
  <Node name="CHA_S1_R_2">
    <Key key="Name" value="Dead Vacuum" />
    <Key key="Description" value="The ability is replaced with:The area of effect is expanded by &lt;w&gt;2&lt;/w&gt; meters. The Destroyer pulls nearby enemies towards him, dealing &lt;pd&gt;physical damage&lt;/pd&gt; and rooting them for &lt;w&gt;3&lt;/w&gt; seconds." />
  </Node>
  <Node name="BOM_S3" />
  <Node name="t5v1">
    <Key key="Name" value="Last Stand" />
    <Key key="Description" value="When receiving lethal damage, the character has a 50% chance to avoid the attack. Additionally, the character regenerates 30% of their missing health over 10 seconds. This effect can only occur once every 5 minutes." />
  </Node>
  <Node name="t5v2">
    <Key key="Name" value="Stoic Endurance" />
    <Key key="Description" value="While under the effect of hard crowd control, the character restores 2% maximum health per second.&#xA;" />
  </Node>
  <Node name="t5v3">
    <Key key="Name" value="Delayed Pain" />
    <Key key="Description" value="If the character's health falls below 20%, all damage taken in the next 5 seconds will be absorbed and dealt over 10 seconds as a damage-over-time effect. This effect can only occur once every 3 minutes." />
  </Node>
  <Node name="WAR_S1_T_1">
    <Key key="Name" value="Combat Renewal" />
    <Key key="Description" value="If the ability charges expire, the Legionary restores &lt;w&gt;0.5%&lt;/w&gt; of maximum HPMax per charge." />
  </Node>
  <Node name="WAR_S1_T_2">
    <Key key="Name" value="Smell of Blood" />
    <Key key="Description" value="The Legionary gains &lt;w&gt;2&lt;/w&gt; charges for a kill and &lt;w&gt;1&lt;/w&gt; charge for assisting in a kill." />
  </Node>
  <Node name="WAR_S1_T_3">
    <Key key="Name" value="Stacking Mastery" />
    <Key key="Description" value="Abilities on hit now also grant &lt;w&gt;1&lt;/w&gt; stack for passive ability." />
  </Node>
  <Node name="WAR_S1_T_4">
    <Key key="Name" value="Fortified Barrier" />
    <Key key="Description" value="When reaching the maximum number of charges, the Legionary gains a shield with a strength of &lt;w&gt;5%&lt;/w&gt; of maximum HPMax + (&lt;w&gt;50%&lt;/w&gt; (Armor + Resist))  for &lt;w&gt;5&lt;/w&gt; seconds." />
  </Node>
  <Node name="WAR_S1_T_5">
    <Key key="Name" value="Throwing Expert" />
    <Key key="Description" value="The Legionary can activate a special ability. The Legionary’s auto-attack range is increased by &lt;w&gt;6&lt;/w&gt; meters when throwing spears. The duration of this effect is increased by &lt;w&gt;1&lt;/w&gt; second for each charge of the special ability." />
  </Node>
  <Node name="WAR_S1_Q_1">
    <Key key="Name" value="Crippling Bash" />
    <Key key="Description" value="The ability slows down affected enemies by &lt;w&gt;20%&lt;/w&gt;." />
  </Node>
  <Node name="WAR_S1_Q_2">
    <Key key="Name" value="Mana Rebound" />
    <Key key="Description" value="If the interrupt was successful, the Legionary restores MPMax to themselves in an amount equal to the interrupt ability's cost." />
  </Node>
  <Node name="WAR_S1_Q_3">
    <Key key="Name" value="Precision Slam" />
    <Key key="Description" value="If the ability hits only one opponent, they are stunned for &lt;w&gt;2&lt;/w&gt; seconds." />
  </Node>
  <Node name="WAR_S1_Q_4">
    <Key key="Name" value="Mirror Shield" />
    <Key key="Description" value="After using the ability, the Legionary gains a shield for &lt;w&gt;2&lt;/w&gt; seconds that reflects the damage from the next incoming ability." />
  </Node>
  <Node name="WAR_S1_Q_5">
    <Key key="Name" value="Earthquake" />
    <Key key="Description" value="The ability can be reactivated within &lt;w&gt;2&lt;/w&gt; seconds. The Legionary strikes the ground with their shield, creating a shockwave in the chosen direction that deals &lt;md&gt;magic damage&lt;/md&gt; and knocks up all affected targets." />
  </Node>
  <Node name="WAR_S1_W_1">
    <Key key="Name" value="Momentum Transfer" />
    <Key key="Description" value="The Legionary throws an ally with precise balance, transferring the momentum of the throw to the ally. The ally's MoveSpeed is increased by &lt;w&gt;20%&lt;/w&gt; for &lt;w&gt;3&lt;/w&gt; seconds upon landing." />
  </Node>
  <Node name="WAR_S1_W_2">
    <Key key="Name" value="Impact Core" />
    <Key key="Description" value="Enemies caught in the center of the affected area receive additional &lt;md&gt;magic damage&lt;/md&gt; equal to &lt;w&gt;10%&lt;/w&gt; of the thrown target's maximum HPMax." />
  </Node>
  <Node name="WAR_S1_W_3">
    <Key key="Name" value="Dominance" />
    <Key key="Description" value="The throwing radius is doubled if target’s maximum HPMax is less than &lt;w&gt;50%&lt;/w&gt; of the Legionary's maximum HPMax." />
  </Node>
  <Node name="WAR_S1_W_4">
    <Key key="Name" value="Perfected Toss" />
    <Key key="Description" value="After landing, the enemy's &lt;armat&gt;Armor&lt;/armat&gt; and Resist are reduced by &lt;w&gt;2%&lt;/w&gt; for each accumulated effect of the special ability. The debuff lasts for &lt;w&gt;3&lt;/w&gt; seconds. After landing an ally, their &lt;armi&gt;&lt;armat&gt;Armor&lt;/armat&gt; and Resist are increased by &lt;w&gt;2%&lt;/w&gt; for each accumulated effect of the special ability. The buff lasts for &lt;w&gt;3&lt;/w&gt; seconds." />
  </Node>
  <Node name="WAR_S1_W_5">
    <Key key="Name" value="Follow-Up Rush" />
    <Key key="Description" value="The ability can be reactivated within &lt;w&gt;2&lt;/w&gt; seconds: The Legionary makes a dash towards the thrown target." />
  </Node>
  <Node name="WAR_S1_E_1">
    <Key key="Name" value="Relentless Provocation" />
    <Key key="Description" value="Taunts vulnerable targets for +&lt;w&gt;1&lt;/w&gt; seconds." />
  </Node>
  <Node name="WAR_S1_E_2">
    <Key key="Name" value="Initial Impact" />
    <Key key="Description" value="Increases the damage dealt to the first affected target by &lt;w&gt;15%&lt;/w&gt;." />
  </Node>
  <Node name="WAR_S1_E_3">
    <Key key="Name" value="Piercing Spear" />
    <Key key="Description" value="The ability ignores &lt;w&gt;20%&lt;/w&gt; of the enemy's Armor." />
  </Node>
  <Node name="WAR_S1_E_4">
    <Key key="Name" value="Cold Steel" />
    <Key key="Description" value="When the ability is on cooldown, Legionary's basic attacks deal additional &lt;pd&gt;physical damage&lt;/pd&gt; (&lt;w&gt;20%&lt;/w&gt; Armor)." />
  </Node>
  <Node name="WAR_S1_E_5">
    <Key key="Name" value="Spear Lunge" />
    <Key key="Description" value="If the ability hits an enemy, it can be reactivated. The Legionary performs a spear lunge, dealing &lt;w&gt;70&lt;/w&gt; - &lt;w&gt;250&lt;/w&gt; (depending on hero level) (AttackPower) &lt;pd&gt;physical damage&lt;/pd&gt;. For each charge of the special ability, the lunge ignores 2% of the enemy's Armor. " />
  </Node>
  <Node name="WAR_S1_R_2">
    <Key key="Name" value="Sacrifice Protection" />
    <Key key="Description" value="The Legionary takes less damage. Each charge of the special ability reduces incoming damage by &lt;w&gt;3%&lt;/w&gt;. Additionaly Legionary can target an ally when using ultimate ablility and redirect &lt;w&gt;50%&lt;/w&gt; incoming damage to this ally to him self for the duration of the ultimate ability. Can retarget protection by pressing R. The duration of the effect is increased by &lt;w&gt;0.5&lt;/w&gt; seconds for each charge of the special ability." />
  </Node>
  <Node name="BOM_S1" />
  <Node name="BOM_S1_NEW" />
  <Node name="WAR_S1_R_1">
    <Key key="Name" value="Resilient Vigor" />
    <Key key="Description" value="Using the ability removes all negative effects from the Legionary, rendering them immune to all crowd control effects and increasing the bonus attack damage gained from Armor and Resist by up to &lt;w&gt;50%&lt;/w&gt;. The duration of the effect is increased by &lt;w&gt;0.5&lt;/w&gt; seconds for each charge of the special ability." />
  </Node>
  <Node name="BOM_S1_T_1">
    <Key key="Name" value="Speed Surge Protocol" />
    <Key key="Description" value="Activating one of the modes increases the Blast Medic's MoveSpeedFinalKPositive by &lt;w&gt;20%&lt;/w&gt; for &lt;w&gt;3&lt;/w&gt; seconds." />
  </Node>
  <Node name="BOM_S1_T_2">
    <Key key="Name" value="Threat Reduction Burst" />
    <Key key="Description" value="Activating a mode causes an energy burst and reduces the Blast Medic's aggro by &lt;w&gt;10%&lt;/w&gt;." />
  </Node>
  <Node name="BOM_S1_T_3">
    <Key key="Name" value="Malfunction: All Modes Engaged" />
    <Key key="Description" value="When selecting a mode, there is a &lt;w&gt;10%&lt;/w&gt; chance of a malfunction. The glitch causes all &lt;w&gt;3&lt;/w&gt; modes to be activated simultaneously." />
  </Node>
  <Node name="BOM_S1_T_4">
    <Key key="Name" value="Upgraded Firmware" />
    <Key key="Description" value="Increases healing and damage effects by &lt;w&gt;10%&lt;/w&gt; and grants an additional auto-attack." />
  </Node>
  <Node name="BOM_S1_T_5">
    <Key key="Name" value="Swift Activation Reset" />
    <Key key="Description" value="The ability can be used again within &lt;w&gt;2&lt;/w&gt; seconds. The mode that was last selected will be chosen automatically. The cost of reusing the ability is &lt;w&gt;20%&lt;/w&gt; of the current MPMax pool, but not less than &lt;w&gt;20&lt;/w&gt; MPMax." />
  </Node>
  <Node name="BOM_S1_Q_1">
    <Key key="Name" value="Rebound Precision" />
    <Key key="Description" value="Increases the projectile's bounces by &lt;w&gt;1&lt;/w&gt;." />
  </Node>
  <Node name="BOM_S1_Q_2">
    <Key key="Name" value="Walking Arsenal" />
    <Key key="Description" value="Blast Medic can move while using this skill, but MoveSpeedFinalKPositive&#xD; is reduced by &lt;w&gt;30%&lt;/w&gt;." />
  </Node>
  <Node name="BOM_S1_Q_3">
    <Key key="Name" value="Extended Ricochet" />
    <Key key="Description" value="Increases the ricochet range to the next target by &lt;w&gt;1&lt;/w&gt; meter." />
  </Node>
  <Node name="BOM_S1_Q_4">
    <Key key="Name" value="Fearsome Mines" />
    <Key key="Description" value="Each ricochet attaches a mine to the enemy for &lt;w&gt;5&lt;/w&gt; seconds, which activates &lt;w&gt;2&lt;/w&gt; seconds after the ricochet. The mine will detonate on the enemy if the Blast Medic shoots it with an auto-attack, dealing &lt;md&gt;magical damage&lt;/md&gt; (&lt;w&gt;50%&lt;/w&gt; SpellPower). The detonation will fear the target for &lt;w&gt;2&lt;/w&gt; seconds. The mine can be dispelled." />
  </Node>
  <Node name="BOM_S1_Q_5">
    <Key key="Name" value="Shielding Echo" />
    <Key key="Description" value=" Each ricochet attaches a mine to an ally for &lt;w&gt;5&lt;/w&gt; seconds, which activates &lt;w&gt;2&lt;/w&gt; seconds after the last ricochet. The Blast Medic can reuse the ability to activate a &lt;shield&gt;shield&lt;/shield&gt; on allies (&lt;w&gt;300%&lt;/w&gt; HLPower) that absorbs damage for &lt;w&gt;5&lt;/w&gt; seconds. The mine can be dispelled." />
  </Node>
  <Node name="BOM_S1_W_1">
    <Key key="Name" value="Speed Guard" />
    <Key key="Description" value="While the shield from this ability is active, the target receives a &lt;w&gt;30%&lt;/w&gt; reduction in slowing effects." />
  </Node>
  <Node name="BOM_S1_W_2">
    <Key key="Name" value="Shattering Blast" />
    <Key key="Description" value="Reduces Armor / Resist of enemies hit by the explosion by &lt;w&gt;20%&lt;/w&gt; for &lt;w&gt;5&lt;/w&gt; seconds." />
  </Node>
  <Node name="BOM_S1_W_3">
    <Key key="Name" value="Prolonged Blindness" />
    <Key key="Description" value="Blind effect +&lt;w&gt;1&lt;/w&gt; second." />
  </Node>
  <Node name="BOM_S1_W_4">
    <Key key="Name" value="Enhanced Blast Zone" />
    <Key key="Description" value="The blast radius is increased, and damage and shield effects are enhanced by &lt;w&gt;20%&lt;/w&gt; at the center of the area." />
  </Node>
  <Node name="BOM_S1_W_5">
    <Key key="Name" value="Smoke Screen Tactics" />
    <Key key="Description" value="After exploding, the bomb turns into a smoke bomb, dispersing a thick smoke cloud in the blast area for &lt;w&gt;5&lt;/w&gt; seconds. The Blast Medic is invisible to enemies while in this cloud. If an enemy enters the smoke cloud, they will see the Bomber and can attack him." />
  </Node>
  <Node name="BOM_S1_E_1">
    <Key key="Name" value="Regenerative Impact" />
    <Key key="Description" value="When the clone hits enemies, the Blast Medic restores &lt;w&gt;5%&lt;/w&gt; + (&lt;w&gt;1%&lt;/w&gt; for every &lt;w&gt;20&lt;/w&gt; HLPower) health." />
  </Node>
  <Node name="BOM_S1_E_2">
    <Key key="Name" value="Explosive Swap" />
    <Key key="Description" value="At the moment of teleportation, a blast occurs at the clone's location, dealing &lt;md&gt;magical damage&lt;/md&gt; equal to &lt;w&gt;100%&lt;/w&gt; SpellPower." />
  </Node>
  <Node name="BOM_S1_E_3">
    <Key key="Name" value="Stunning Transposition" />
    <Key key="Description" value="When the Blast Medic teleports through an enemy, the enemy is stunned for &lt;w&gt;2&lt;/w&gt; seconds." />
  </Node>
  <Node name="BOM_S1_E_4">
    <Key key="Name" value="Controlled Decoy" />
    <Key key="Description" value="The Blast Medic can control their clone.&#xA;You can automatically teleport by using Shift +E." />
  </Node>
  <Node name="BOM_S1_E_5">
    <Key key="Name" value="Twin Swap Sequence" />
    <Key key="Description" value="Can re-use the ability within &lt;w&gt;2&lt;/w&gt; seconds to swap places with the clone back." />
  </Node>
  <Node name="BOM_S1_R1">
    <Key key="Name" value="Omni-Assist Module" />
    <Key key="Description" value="- Removes all crowd control effects from an ally.&#xD;&#xA;- While the Blast Medic is under the shield, he regenerates health at &lt;w&gt;2%&lt;/w&gt; of maximum HPMax per second.&#xD;&#xA;- While the enemy is under the drone's effect, they take &lt;w&gt;15%&lt;/w&gt; more incoming damage." />
  </Node>
  <Node name="BOM_S1_R2">
    <Key key="Name" value="Fear Cascade Detonation Device" />
    <Key key="Description" value="The Blast Medic throws a drone at the target, dealing damage (&lt;w&gt;150%&lt;/w&gt; AttackPower and &lt;w&gt;150%&lt;/w&gt; SpellPower) and causing fear for &lt;w&gt;2&lt;/w&gt; seconds. After the debuff expires, the drone detonates (radius &lt;w&gt;2&lt;/w&gt;m), dealing damage (&lt;w&gt;150%&lt;/w&gt; AttackPower and &lt;w&gt;150%&lt;/w&gt; SpellPower) and causing fear for &lt;w&gt;2&lt;/w&gt; seconds to all enemies within the explosion radius." />
  </Node>
  <Node name="CHA_S2_W_5">
    <Key key="Description" value="The Ranger uses acid arrows and leaves an acidic cloud in the area of effect for &lt;w&gt;5&lt;/w&gt; seconds. Enemies within the area receive magic damage over time (&lt;w&gt;100%&lt;/w&gt; SpellPower) each second. If the acidic cloud connects with fire the area will explode for (&lt;w&gt;100%&lt;/w&gt; SpellPower) &lt;md&gt;magic damage&lt;/md&gt;." />
    <Key key="Name" value="Acidic Barrage" />
  </Node>
  <Node name="h5v3">
    <Key key="Name" value="Focus Healing" />
    <Key key="Description" value="Each character's healing or shielding used on the same target increases the healing and shielding used on that same target by 5%. The effect stacks up to 5 times and lasts for 15 seconds. If an ability is used on a different target, the buff expires." />
  </Node>
  <Node name="h5v1">
    <Key key="Name" value="Mystic Transference" />
    <Key key="Description" value="Healing an ally increases the effectiveness of next damaging ability by 15%. Damaging an enemy with ability increases the effectiveness of next healing ability by 15%" />
  </Node>
  <Node name="h5v2">
    <Key key="Name" value="Ultima Resonance" />
    <Key key="Description" value="Using the ultimate ability reduces the cost of healing abilities by 90% for 20 seconds." />
  </Node>
  <Node name="CHA_S2_Q_1">
    <Key key="Description" value="The net becomes denser and restricts movements. For those affected by the skill, AttackSpeed is reduced by &lt;w&gt;50%&lt;/w&gt;, and the casting speed of abilities is also decreased by &lt;w&gt;50%&lt;/w&gt;." />
    <Key key="Name" value="Binding net" />
  </Node>
  <Node name="CHA_S2_Q_2">
    <Key key="Description" value="If the ability affects an opponent who is under the acceleration buff or flying, the target receives double damage." />
    <Key key="Name" value="Speedstalker" />
  </Node>
  <Node name="CHA_S2_Q_3">
    <Key key="Description" value="The net becomes acidic, during the immobilization effect, the target's Armor and Resist are reduced by &lt;w&gt;5%&lt;/w&gt; each second for &lt;w&gt;5&lt;/w&gt; seconds." />
    <Key key="Name" value="Corrosive Restraint" />
  </Node>
  <Node name="CHA_S2_Q_4">
    <Key key="Description" value="The ability also immobilizes one additional enemy located &lt;w&gt;3&lt;/w&gt; meters behind the primary target." />
    <Key key="Name" value="Backline Snare" />
  </Node>
  <Node name="CHA_S2_Q_5">
    <Key key="Description" value="If the ability immobilizes an opponent, the skill can be reused - the Ranger releases a fiery arrow in the specified direction. The arrow deals &lt;pd&gt;physical damage&lt;/pd&gt; (&lt;w&gt;100%&lt;/w&gt; AttackPower) and ignites the target it hits applying &lt;md&gt;magic damage&lt;/md&gt; over time &lt;w&gt;10&lt;/w&gt;/&lt;w&gt;20&lt;/w&gt;/&lt;w&gt;30&lt;/w&gt;/&lt;w&gt;40&lt;/w&gt;/&lt;w&gt;50&lt;/w&gt;+ (&lt;w&gt;70%&lt;/w&gt; SpellPower) for &lt;w&gt;3&lt;/w&gt; seconds. Enemies immobilized by the ability are ignited for &lt;w&gt;6&lt;/w&gt; seconds, but the root effect fades after &lt;w&gt;0.5&lt;/w&gt; sec." />
    <Key key="Name" value="Inferno Arrow" />
  </Node>
  <Node name="CHA_S2_W_1">
    <Key key="Description" value="The Ability now applies &lt;w&gt;1&lt;/w&gt; arrow for The Ranger’s passive ability to all enemies affected." />
    <Key key="Name" value="Area Marksmanship" />
  </Node>
  <Node name="CHA_S2_W_2">
    <Key key="Description" value="The radius of the ability is increased by &lt;w&gt;1&lt;/w&gt; meter and deals &lt;w&gt;20%&lt;/w&gt; more damage in the center of the effect." />
    <Key key="Name" value="Focal Point" />
  </Node>
  <Node name="CHA_S2_W_3">
    <Key key="Description" value="Enemies within the area of effect are unable to use dash abilities." />
    <Key key="Name" value="Mobility Suppression" />
  </Node>
  <Node name="CHA_S2_W_4">
    <Key key="Description" value="The skill gains &lt;w&gt;2&lt;/w&gt; charges. " />
    <Key key="Name" value="Dual Capacity" />
  </Node>
  <Node name="CHA_S2_E_1">
    <Key key="Description" value="While the Ranger is in the standard stance, he ignores &lt;w&gt;2%&lt;/w&gt; of the target's Armor for each lodged arrow." />
    <Key key="Name" value="Armor Penetration Expertise" />
  </Node>
  <Node name="CHA_S2_E_2">
    <Key key="Description" value="While the Ranger is in the barrage stance, additional targets recieve &lt;w&gt;75%&lt;/w&gt; damage." />
    <Key key="Name" value="Multishot Mastery" />
  </Node>
  <Node name="CHA_S2_E_3">
    <Key key="Description" value="Upon switching to the standard stance, the next auto-attack disarms the target for &lt;w&gt;2&lt;/w&gt; seconds. Upon switching to the barrage stance, the next auto-attack knocks back enemies by &lt;w&gt;2&lt;/w&gt; meters." />
    <Key key="Name" value="Stance Switcheryr E3" />
  </Node>
  <Node name="CHA_S2_E_4">
    <Key key="Description" value="Every 5th shot deals &lt;w&gt;5%&lt;/w&gt; of the opponent's current HPMax as &lt;md&gt;magic damage&lt;/md&gt;." />
    <Key key="Name" value="Silver Arrow" />
  </Node>
  <Node name="CHA_S2_E_5">
    <Key key="Description" value="The Ranger coats the arrow with poison over &lt;w&gt;1.5&lt;/w&gt; seconds (shift E) and can be cast while moving. After the arrow is coated, the Ranger can release the arrow in the desired direction within &lt;w&gt;3&lt;/w&gt; seconds. The poison arrow deals &lt;pd&gt;physical damage&lt;/pd&gt; (&lt;w&gt;100%&lt;/w&gt; AttackPower) and applies a poison effect to the target it hits, dealing &lt;md&gt;magic damage&lt;/md&gt; over time (&lt;w&gt;10&lt;/w&gt;/&lt;w&gt;20&lt;/w&gt;/&lt;w&gt;30&lt;/w&gt;/&lt;w&gt;40&lt;/w&gt;/&lt;w&gt;50&lt;/w&gt; + &lt;w&gt;70%&lt;/w&gt; SpellPower) for &lt;w&gt;3&lt;/w&gt; seconds. If the poison arrow hits an acidic net, the effect of the acidic net is doubled. If the poison arrow hits an acidic cloud, the effect and duration of the acidic cloud are doubled." />
    <Key key="Name" value="Venomous Infusion" />
  </Node>
  <Node name="CHA_S2_T_1">
    <Key key="Description" value="The Ranger moves &lt;w&gt;15%&lt;/w&gt; faster when moving towards a target with &lt;w&gt;5&lt;/w&gt; or more arrows." />
    <Key key="Name" value="Arrow Chaser" />
  </Node>
  <Node name="CHA_S2_T_2">
    <Key key="Description" value="Increases the chance a target will be hit by an additional arrow by &lt;w&gt;10%&lt;/w&gt;." />
    <Key key="Name" value="Follow-up Shaft" />
  </Node>
  <Node name="CHA_S2_T_3">
    <Key key="Description" value="Upon activating the ability, the Ranger restores &lt;w&gt;0.5%&lt;/w&gt; of his maximum HPMax for each arrow." />
    <Key key="Name" value="Vital Quiver Restoration" />
  </Node>
  <Node name="CHA_S2_T_4">
    <Key key="Description" value="If a target has the maximum amount of arrows stacked, they will slowly drain &lt;w&gt;1&lt;/w&gt; mana per arrow per second." />
    <Key key="Name" value="Mana Drain Barrage" />
  </Node>
  <Node name="CHA_S2_T_5">
    <Key key="Description" value="At &lt;w&gt;6&lt;/w&gt; stacks of the special ability, the archer's auto-attacks deal additional &lt;md&gt;magic damage&lt;/md&gt; (&lt;w&gt;15%&lt;/w&gt; SpellPower)." />
    <Key key="Name" value="Hexashot Enhancement" />
  </Node>
  <Node name="CHA_S2_R_1">
    <Key key="Description" value="A shot with fiery arrows. At the landing point of the arrows (at the end of the cone), a fiery wall appears. Enemies passing through it take &lt;md&gt;magical damage&lt;/md&gt; (&lt;w&gt;40%&lt;/w&gt; SpellPower) each second and ignite, receiving magical damage over time (&lt;w&gt;100%&lt;/w&gt; SpellPower) for &lt;w&gt;5&lt;/w&gt; seconds." />
    <Key key="Name" value="Fire Volley" />
  </Node>
  <Node name="CHA_S2_R_2">
    <Key key="Description" value="After a successful rebound, the ability can be activated again. The Ranger performs a powerful fire shot in the specified direction. The shot deals &lt;pd&gt;physical damage&lt;/pd&gt; (&lt;w&gt;140%&lt;/w&gt; AttackPower) to the first target hit and leaves behind &lt;w&gt;3&lt;/w&gt; charges of the passive ability." />
    <Key key="Name" value="Blaze Rebounder" />
  </Node>
  <Node name="Stacking Strength" />
  <Node name="Warrior" />
  <Node name="WAR_S3_Q_1">
    <Key key="Name" value="Balance Breaker" />
    <Key key="Description" value="Shaman's Leap disrupts the target's balance and interrupts ability usage." />
  </Node>
  <Node name="WAR_S3_Q_2">
    <Key key="Name" value="Accelerated Assault" />
    <Key key="Description" value="After the leap, the shaman harnesses the movement impulse, granting the next &lt;w&gt;4&lt;/w&gt; auto-attacks &lt;w&gt;100%&lt;/w&gt; increased AttackSpeed." />
  </Node>
  <Node name="WAR_S3_Q_3">
    <Key key="Name" value="Versatile Movement" />
    <Key key="Description" value="The shaman is able to jump to allied targets." />
  </Node>
  <Node name="WAR_S3_Q_4">
    <Key key="Name" value="Rending Knuckles" />
    <Key key="Description" value="The shaman plunges his knuckles into an enemy target, leaving gaping wounds that deal periodic &lt;pd&gt;physical damage&lt;/pd&gt; equal to &lt;w&gt;100%&lt;/w&gt; AttackPower over &lt;w&gt;5&lt;/w&gt; seconds." />
  </Node>
  <Node name="WAR_S3_Q_5">
    <Key key="Name" value="Swift Roll" />
    <Key key="Description" value="The shaman can use the ability again within &lt;w&gt;1&lt;/w&gt; second after the leap to roll behind the enemy." />
  </Node>
  <Node name="WAR_S3_E_1">
    <Key key="Name" value="Lightning Recoil" />
    <Key key="Description" value="The first target hit by the lightning is knocked back &lt;w&gt;1&lt;/w&gt; meter." />
  </Node>
  <Node name="WAR_S3_E_2">
    <Key key="Name" value="Electrifying Aftershock" />
    <Key key="Description" value="If the ability deals critical damage, it leaves electric charges on the target, inflicting periodic &lt;md&gt;magical damage&lt;/md&gt; equal to &lt;w&gt;50%&lt;/w&gt; SpellPower over &lt;w&gt;5&lt;/w&gt; seconds." />
  </Node>
  <Node name="WAR_S3_E_3">
    <Key key="Name" value="Dual Lightning Strikes" />
    <Key key="Description" value="The ability has &lt;w&gt;2&lt;/w&gt; charges." />
  </Node>
  <Node name="WAR_S3_E_4">
    <Key key="Name" value="Chain Lightning" />
    <Key key="Description" value="The shaman delves deeper into the knowledge of the air element, making his lightning more destructive. The lightning turns into a chain lightning that strikes up to &lt;w&gt;4&lt;/w&gt; targets, with each next target receiving &lt;w&gt;50%&lt;/w&gt; less damage." />
  </Node>
  <Node name="WAR_S3_E_5">
    <Key key="Name" value="Recursive Chain" />
    <Key key="Description" value="The lightning can bounce between the same targets if no other targets are available." />
  </Node>
  <Node name="WAR_S3_T_1">
    <Key key="Name" value="Prolonged Haste" />
    <Key key="Description" value="The AttackSpeed buff lasts for &lt;w&gt;15&lt;/w&gt; seconds." />
  </Node>
  <Node name="WAR_S3_T_2">
    <Key key="Name" value="Enhanced Charge Accumulation" />
    <Key key="Description" value="Rip Apart and Lightning Strike can apply a charge of the special ability." />
  </Node>
  <Node name="WAR_S3_T_3">
    <Key key="Name" value="Distance Boost" />
    <Key key="Description" value="Each stack adds +&lt;w&gt;1&lt;/w&gt; meter range to Rip Apart and Lightning Strike." />
  </Node>
  <Node name="WAR_S3_T_4">
    <Key key="Name" value="Charge Overflow" />
    <Key key="Description" value="There is a &lt;w&gt;20%&lt;/w&gt; chance to stack &lt;w&gt;2&lt;/w&gt; charges at once instead of one when gaining charges." />
  </Node>
  <Node name="WAR_S3_T_5">
    <Key key="Name" value="Elemental Synergy" />
    <Key key="Description" value="Fire Element - Knuckles ignite, causing the shaman to deal additional &lt;md&gt;magical damage&lt;/md&gt; with auto-attacks (&lt;w&gt;20%&lt;/w&gt; SpellPower).&#xD;&#xA;Water Element - Restores MPMax with auto-attacks (&lt;w&gt;2%&lt;/w&gt; of damage dealt).&#xD;&#xA;Earth Element - Skin hardens, reducing enemy auto-attack damage by &lt;w&gt;15%&lt;/w&gt;." />
  </Node>
  <Node name="WAR_S3_W_2">
    <Key key="Name" value="Expanded Influence" />
    <Key key="Description" value="Increases the totem's effective radius by &lt;w&gt;30%&lt;/w&gt;." />
  </Node>
  <Node name="WAR_S3_W_1">
    <Key key="Name" value="Extended Totem" />
    <Key key="Description" value="Increases the totem's duration by &lt;w&gt;5&lt;/w&gt; seconds." />
  </Node>
  <Node name="WAR_S3_W_3">
    <Key key="Name" value="Fortified Totems" />
    <Key key="Description" value="The shaman's totems become sturdier and gain &lt;w&gt;+2&lt;/w&gt; HPMax." />
  </Node>
  <Node name="WAR_S3_W_4">
    <Key key="Name" value="Elemental Efficiency" />
    <Key key="Description" value="There is a &lt;w&gt;10%&lt;/w&gt; chance that the totem won't consume a stack." />
  </Node>
  <Node name="WAR_S3_W_5">
    <Key key="Name" value="Totemic Empowerment" />
    <Key key="Description" value="Healing Totem - Cleanses one debuff from the shaman or an ally every &lt;w&gt;5&lt;/w&gt; seconds.&#xD;&#xA;Fire Totem - Attacks &lt;w&gt;2&lt;/w&gt; targets simultaneously.&#xD;&#xA;Wolf Totem - Reduces enemy MoveSpeed by &lt;w&gt;20%&lt;/w&gt;." />
  </Node>
  <Node name="WAR_S3_R_1">
    <Key key="Name" value="Spirits Fusion" />
    <Key key="Description" value="The spirit of the wolf inhabits the shaman, enhancing his abilities.&#xD;&#xA;• Rip Apart - Empowers the next auto-attack within &lt;w&gt;2&lt;/w&gt; seconds.&#xD;&#xA;• Totemic Fury - The shaman gains &lt;w&gt;+100%&lt;/w&gt; to the skill's passive buffs.&#xD;&#xA;• Lightning Strike - No cooldown. &#xD;&#xA;Consumes &lt;w&gt;10&lt;/w&gt; MPMax per second. &#xD;&#xA;Press Shift+R." />
  </Node>
  <Node name="WAR_S3_R_2">
    <Key key="Name" value="Empowered Direwolf Form" />
    <Key key="Description" value="The summoned wolf receives &lt;w&gt;10%&lt;/w&gt; + (&lt;w&gt;1%&lt;/w&gt; for every &lt;w&gt;25&lt;/w&gt; SpellPower) of the shaman's stats. It increases in size and generates increased threat with its attacks.&#xD;&#xA;When recast on a friendly target, the wolf establishes a spiritual bond with them.&#xD;&#xA;Gains the Claw Strike ability (recast the skill on an enemy, costs &lt;w&gt;75&lt;/w&gt; MPMax), which hits in a cone in front of it, dealing (&lt;w&gt;40&lt;/w&gt;/&lt;w&gt;80&lt;/w&gt;/&lt;w&gt;120&lt;/w&gt;/&lt;w&gt;160&lt;/w&gt;/&lt;w&gt;200&lt;/w&gt;) + (&lt;w&gt;40%&lt;/w&gt;/&lt;w&gt;60%&lt;/w&gt;/&lt;w&gt;70%&lt;/w&gt;/&lt;w&gt;80%&lt;/w&gt;/&lt;w&gt;90%&lt;/w&gt;) AttackPower and provoking affected enemies to attack it for 1 second while healing the bonded ally for (&lt;w&gt;30%&lt;/w&gt; of damage dealt + &lt;w&gt;50%&lt;/w&gt; HLPower).&#xD;&#xA;Cooldown is &lt;w&gt;15&lt;/w&gt; seconds.&#xD;&#xA;Consumes &lt;w&gt;10&lt;/w&gt; MPMax per second.&#xD;&#xA;Press Shift+R." />
  </Node>
  <Node name="Tank" />
  <Node name="Crafter" />
  <Node name="BOM_S3_Q1">
    <Key key="Name" value="Shadow Grace" />
    <Key key="Description" value="MoveSpeedFinalKPositive in camouflage is increased by &lt;w&gt;20%&lt;/w&gt;." />
  </Node>
  <Node name="BOM_S3_Q2">
    <Key key="Name" value="Flurry" />
    <Key key="Description" value="When leaving invisibility, AttackSpeed is increased by &lt;w&gt;20%&lt;/w&gt; for &lt;w&gt;4&lt;/w&gt; seconds." />
  </Node>
  <Node name="BOM_S3_Q3">
    <Key key="Name" value="Vanish Device" />
    <Key key="Description" value="The new generation camouflage device allows for instant invisibility." />
  </Node>
  <Node name="BOM_S3_Q4">
    <Key key="Name" value="Advanced Cloaking Algorithm" />
    <Key key="Description" value="Upgraded camouflage enables you to sneak closer to enemies." />
  </Node>
  <Node name="BOM_S3_Q5">
    <Key key="Name" value="Ambush" />
    <Key key="Description" value="The Infiltrator has learned the Ambush skill. While in camouflage, the Infiltrator can deliver a powerful strike to an enemy. This attack always deals critical damage." />
  </Node>
  <Node name="BOM_S3_W1">
    <Key key="Name" value="Stunning Grenade" />
    <Key key="Description" value="If the mine lands on an enemy, they will be stunned for &lt;w&gt;2&lt;/w&gt; seconds." />
  </Node>
  <Node name="BOM_S3_W2">
    <Key key="Name" value="Dazzler" />
    <Key key="Description" value="The Infiltrator uses an advanced version of the mine with a flash effect. Enemies caught in the blast radius are also blinded for &lt;w&gt;2&lt;/w&gt; seconds." />
  </Node>
  <Node name="BOM_S3_W3">
    <Key key="Name" value="Minefield Deployment" />
    <Key key="Description" value="Up to &lt;w&gt;3&lt;/w&gt; mines can be active simultaneously." />
  </Node>
  <Node name="BOM_S3_W4">
    <Key key="Name" value="Stealthy Sabotage" />
    <Key key="Description" value="The Infiltrator can throw a mine from stealth without breaking it." />
  </Node>
  <Node name="BOM_S3_W5">
    <Key key="Name" value="Chain Reaction" />
    <Key key="Description" value="Press Shift+R to cause mines within a &lt;w&gt;14&lt;/w&gt;-meter radius to rise into the air (&lt;w&gt;0.3&lt;/w&gt; seconds) and explode, doubling their blast radius. When hit by more than one mine, only &lt;w&gt;25%&lt;/w&gt; of the damage from each additional mine is counted." />
  </Node>
  <Node name="BOM_S3_E1">
    <Key key="Name" value="Blitz" />
    <Key key="Description" value="MoveSpeedFinalKPositive increases by &lt;w&gt;20%&lt;/w&gt; towards the rooted target. Activates from &lt;w&gt;2&lt;/w&gt; meters and farther." />
  </Node>
  <Node name="BOM_S3_E2">
    <Key key="Name" value="Defense Breakthrough" />
    <Key key="Description" value="While the target is rooted, its defense stats are reduced by &lt;w&gt;30%&lt;/w&gt;." />
  </Node>
  <Node name="BOM_S3_E3">
    <Key key="Name" value="Extended Payload" />
    <Key key="Description" value="The Infiltrator grenade cluster now has twice as many grenades. (Blast radius increased by &lt;w&gt;1&lt;/w&gt; meter)" />
  </Node>
  <Node name="BOM_S3_E4">
    <Key key="Name" value="Static Field" />
    <Key key="Description" value="After the explosion, a electric zone remains, dealing damage every second equivalent to &lt;w&gt;30%&lt;/w&gt; of SpellPower to all enemies within it for &lt;w&gt;5&lt;/w&gt; seconds." />
  </Node>
  <Node name="BOM_S3_E5">
    <Key key="Name" value="Interdiction Protocol" />
    <Key key="Description" value="If a healing or shield spell is applied to the rooted target, the caster will be rooted  for &lt;w&gt;2&lt;/w&gt; seconds, silenced for &lt;w&gt;5&lt;/w&gt; seconds, and their ability's will be interupted." />
  </Node>
  <Node name="BOM_S3_T1">
    <Key key="Name" value="Toxic Blades" />
    <Key key="Description" value="The Infiltrator poisons the daggers before throwing,  causing enemies to take additional damage equal to &lt;w&gt;20%&lt;/w&gt; SpellPower over &lt;w&gt;7&lt;/w&gt; seconds. This effect can stack." />
  </Node>
  <Node name="BOM_S3_T2">
    <Key key="Name" value="Lethal Precision" />
    <Key key="Description" value="If the dagger hits from behind, the damage will always be critical." />
  </Node>
  <Node name="BOM_S3_T3">
    <Key key="Name" value="Fleet Footwork" />
    <Key key="Description" value="For each dagger that hits the target, the Infiltrator gains a &lt;w&gt;10%&lt;/w&gt; MoveSpeed increase for &lt;w&gt;5&lt;/w&gt; seconds." />
  </Node>
  <Node name="BOM_S3_T4">
    <Key key="Name" value="Hemorrhage" />
    <Key key="Description" value="If both daggers hit one target, the Infiltrator starts to drain life from the target through his daggers, draining 2% of the target's maximum Health each second." />
  </Node>
  <Node name="BOM_S3_T5">
    <Key key="Name" value="Elimination" />
    <Key key="Description" value="Recast T: With shadow chains, the Infiltrator pulls his daggers back from the victim, dealing &lt;w&gt;60%&lt;/w&gt; SpellPower damage for each dagger and causing a Bleed effect that deals &lt;w&gt;30%&lt;/w&gt; AttackPower damage per second for &lt;w&gt;5&lt;/w&gt; seconds. Additionally, it removes any disarm effect from the Bomber." />
  </Node>
  <Node name="BOM_S3_R1">
    <Key key="Name" value="Shadow Step" />
    <Key key="Description" value="The Infiltrator shadow steps behind the enemy and delivers a dual dagger strike that deals (100%)AttackPower. The skill has &lt;w&gt;3&lt;/w&gt; charges. If the target's HPMax is at &lt;w&gt;20%&lt;/w&gt; or below, the Infiltrator deals &lt;w&gt;20%&lt;/w&gt; more damage." />
  </Node>
  <Node name="BOM_S3_R2">
    <Key key="Name" value="Fade Away" />
    <Key key="Description" value="After using the ultimate ability, if the skill hasn't recharged, the Infiltrator can enter stealth for &lt;w&gt;7&lt;/w&gt; seconds within the next &lt;w&gt;2&lt;/w&gt; seconds. This removes all aggro." />
  </Node>
  <Node name="ORC_S3" />
  <Node name="ORC_S1" />
  <Node name="CHA_S3_R2" />
  <Node name="CHA_S3_R1" />
  <Node name="CHA_S3_E5" />
  <Node name="CHA_S3_T1" />
</Category>