<?xml version='1.0' encoding='utf-8'?>
<Node name="QuestLocalization_info_balthazar_baz_grimble" type="external">
  <Key key="_npc_Hic__name_s_Balthazar____but_f" value="HIC, el nombre es Balthazar ... pero la gente de Jus me llama Baz." voiceSettingsId="VTNqb7LLkURec37jtcR6" />
  <Key key="_npc_Used_to_be_a_top_notch_mixer_o" value="Solía ​​ser una mezcladora de bebidas de primer nivel en Elan, ¿sí?" voiceSettingsId="VTNqb7LLkURec37jtcR6" />
  <Key key="_npc_Could_whip_up_a_potion_to_make" value="Podría preparar una poción para hacer que tus problemas desaparezcan ... o tu mente deambulando en algún lugar encantador." voiceSettingsId="VTNqb7LLkURec37jtcR6" />
  <Key key="_npc_But__y_know__got_too_fond_of_m" value="Pero, ya sabes, me gustan demasiado las propias cervezas, me perdieron el cabello y me asuntos." voiceSettingsId="VTNqb7LLkURec37jtcR6" />
  <Key key="_npc_hic___Ah__never_better__mate_" value="hic - Ah, never better, mate!" voiceSettingsId="VTNqb7LLkURec37jtcR6" />
  <Key key="_npc_Life_s_a_bloody_rollercoast_r_" value="La vida es un sangriento rollercoast'r cuando tienes una botella en tu mano." voiceSettingsId="VTNqb7LLkURec37jtcR6" />
  <Key key="_npc_Jus__had_a_couple_o__patrons__" value="Jus 'tenía un par de o' clientes ... malditos pesos livianos, se desmayaron a los fríos eructos." voiceSettingsId="VTNqb7LLkURec37jtcR6" />
  <Key key="_npc_Ain_t_no_rest_for_the_wicked__" value="No hay descanso para los malvados, ¿verdad?¡Jajaja!" voiceSettingsId="VTNqb7LLkURec37jtcR6" />
  <Key key="_npc_Been_mixin__up_me_special_brew" value="He estado mezclando cervezas especiales ... poniendo a la gente para dormir más rápido que una canción de cuna, je." voiceSettingsId="VTNqb7LLkURec37jtcR6" />
  <Key key="_npc_Ya_lookin__for_a_good_time_or_" value="¿Estás buscando un buen momento o un viaje arriesgado?" voiceSettingsId="VTNqb7LLkURec37jtcR6" />
  <Key key="_npc_Ah__this_lil__haven__Welcome_t" value="Ah, este lil 'Haven?Bienvenido a Baz S ... hic ... mejor, amigo." voiceSettingsId="VTNqb7LLkURec37jtcR6" />
  <Key key="_npc_Used_ta_be_jus__plain_ol__wood" value="Usado para ser jus 'Plain Ol' Woods cerca de la casa de carretera ... pero vi potencial, ¿sabes?" voiceSettingsId="VTNqb7LLkURec37jtcR6" />
  <Key key="_npc_Those_rich_bastards_at_the_Roa" value="Esos bastardos ricos en el roadhouse tienen bolsillos profundos.HIC." voiceSettingsId="VTNqb7LLkURec37jtcR6" />
  <Key key="_npc_Figured_I_d_set_up_shop_here__" value="Supuse que había instalado una tienda aquí ... hic ... enganchar a algunos de ellos passando los rollers." voiceSettingsId="VTNqb7LLkURec37jtcR6" />
  <Key key="_npc_Ah__ya_big_ol__sweetheart_" value="¡Ah, gran cariño!" voiceSettingsId="VTNqb7LLkURec37jtcR6" />
  <Key key="_npc_Got_sum_passed_out_sots_need_d" value="Suma que se desmayó los Sots necesitan volcar." voiceSettingsId="VTNqb7LLkURec37jtcR6" />
  <Key key="_npc_Heh__yer_a_gem_fer_askin__" value="Je, tu gema para preguntar." voiceSettingsId="VTNqb7LLkURec37jtcR6" />
  <Key key="_npc_How__bout_helpin__rid_me_o__th" value="¿Cómo &quot;ayudarme&quot; librarme de las bebidas &quot;las piñones&quot;, eh?" voiceSettingsId="VTNqb7LLkURec37jtcR6" />
  <Key key="_npc_Heeey____could_use_a_hand_refi" value="Heeey ... podría usar una mano rellenada esta barra aquí." voiceSettingsId="VTNqb7LLkURec37jtcR6" />
  <Key key="_npc_Don_t_want_the_next_sucker_run" value="No quiero que el próximo tonto sea seco, ¿me sientes?" voiceSettingsId="VTNqb7LLkURec37jtcR6" />
  <Key key="_npc_Got_sum_dead_weight__round_her" value="Tengo una suma de peso muerto." voiceSettingsId="VTNqb7LLkURec37jtcR6" />
  <Key key="_npc_Help_ol__Baz_toss__em_out__eh_" value="Ayude a Ol 'Baz arrojarlos, ¿eh?" voiceSettingsId="VTNqb7LLkURec37jtcR6" />
  <Key key="_npc_Hic____kinda_ya_ta_offer_" value="Hic ... ¡¡¡¡¡¡¡¡¡¡¡¡¡¡¡¡¡¡¡¡¡¡¡¡¡¡¡¡¡¡¡¡¡¡¡¡¡¡¡¡¡¡¡¡¡¡¡¡¡¡¡¡¡¡¡¡¡¡¡¡¡" voiceSettingsId="VTNqb7LLkURec37jtcR6" />
  <Key key="_npc_Ever_play_bartender_" value="¿Alguna vez ha jugado barman?" voiceSettingsId="VTNqb7LLkURec37jtcR6" />
  <Key key="_npc_How__bout_restockin__my_stash_" value="¿Cómo 'reabastece mi alijo?¡HIC, no me arrepentirá!" voiceSettingsId="VTNqb7LLkURec37jtcR6" />
  <Key key="_npc_Nah__mate__jus__keep_me_compan" value="Nah, mate, jus' keep me company fer a drink, eh?" voiceSettingsId="VTNqb7LLkURec37jtcR6" />
  <Key key="_npc_Help__I_m_good____unless_ya_co" value="¿Ayuda?Estoy bien ... a menos que tengas en cuenta esta botella." voiceSettingsId="VTNqb7LLkURec37jtcR6" />
  <Key key="_npc_hic_Naw__but____how_s__bout_a_" value="hic Naw, but... how's 'bout a drink, pal?" voiceSettingsId="VTNqb7LLkURec37jtcR6" />
  <Key key="_npc_Piss_off__But_stay_fer_a_drink" value="¡PISS!Pero quédate con una bebida o dos." voiceSettingsId="VTNqb7LLkURec37jtcR6" />
  <Key key="_npc_Hell_no__eedin__nothin__but_ol" value="¡Demonios no, eedin 'Nothin' sino una compañía de bebidas!" voiceSettingsId="VTNqb7LLkURec37jtcR6" />
</Node>